{
	"info": {
		"_postman_id": "51beff3f-2f96-4388-ae33-2b44c97242b5",
		"name": "Requis",
		"schema": "https://schema.getpostman.com/json/collection/v2.1.0/collection.json",
		"_exporter_id": "23141320"
	},
	"item": [
		{
			"name": "Get data",
			"event": [
				{
					"listen": "test",
					"script": {
						"exec": [
							""
						],
						"type": "text/javascript"
					}
				}
			],
			"request": {
				"method": "GET",
				"header": [],
				"url": {
					"raw": "{{baseurl}}/api/users/2",
					"host": [
						"{{baseurl}}"
					],
					"path": [
						"api",
						"users",
						"2"
					]
				}
			},
			"response": []
		},
		{
			"name": "post data",
			"event": [
				{
					"listen": "test",
					"script": {
						"exec": [
							"var jsondata = pm.response.json();\r",
							"\r",
							"pm.environment.set(\"userid\",jsondata.id);\r",
							"pm.environment.set(\"username\", jsondata.name);\r",
							"\r",
							"pm.test(\"test user name\", function () {\r",
							"    pm.expect(jsondata.name).to.eql(pm.environment.get(\"username\"))\r",
							"\r",
							"});\r",
							"\r",
							"pm.test(\"Content-Type is present\", function () {\r",
							"    pm.response.to.have.header(\"Content-Type\");\r",
							"});\r",
							"\r",
							"pm.test(\"Status code is 200\", function () {\r",
							"    pm.response.to.have.status(201);\r",
							"});\r",
							"\r",
							"pm.test(\"Response time is less than 200ms\", function () {\r",
							"    pm.expect(pm.response.responseTime).to.be.below(556);\r",
							"});"
						],
						"type": "text/javascript"
					}
				}
			],
			"request": {
				"method": "POST",
				"header": [],
				"body": {
					"mode": "raw",
					"raw": "{\r\n    \"name\": \"morpheus\",\r\n    \"job\": \"leader\"\r\n}",
					"options": {
						"raw": {
							"language": "json"
						}
					}
				},
				"url": {
					"raw": "{{baseurl}}/api/users",
					"host": [
						"{{baseurl}}"
					],
					"path": [
						"api",
						"users"
					]
				}
			},
			"response": []
		},
		{
			"name": "put data",
			"event": [
				{
					"listen": "test",
					"script": {
						"exec": [
							"pm.test(\"Successful POST request\", function () {\r",
							"    pm.expect(pm.response.code).to.be.oneOf([200, 201]);\r",
							"\r",
							"});\r",
							"\r",
							"pm.test(\"Response body contains 'name', 'job', and 'updatedAt' properties\", function () {\r",
							"    var jsonData = pm.response.json();\r",
							"    pm.expect(jsonData).to.have.all.keys('name', 'job', 'updatedAt');\r",
							"});\r",
							"\r",
							"pm.test(\"Properties 'name', 'job', and 'updatedAt' are of type 'string'\", function () {\r",
							"    var jsonData = pm.response.json();\r",
							"    pm.expect(jsonData.name).to.be.a('string');\r",
							"    pm.expect(jsonData.job).to.be.a('string');\r",
							"    pm.expect(jsonData.updatedAt).to.be.a('string');\r",
							"});"
						],
						"type": "text/javascript"
					}
				}
			],
			"request": {
				"method": "PUT",
				"header": [],
				"body": {
					"mode": "raw",
					"raw": "{\r\n    \"name\": \"morpheus\",\r\n    \"job\": \"zion resident\"\r\n}",
					"options": {
						"raw": {
							"language": "json"
						}
					}
				},
				"url": {
					"raw": "{{baseurl}}/api/users/2",
					"host": [
						"{{baseurl}}"
					],
					"path": [
						"api",
						"users",
						"2"
					]
				}
			},
			"response": []
		},
		{
			"name": "patch data",
			"request": {
				"method": "PATCH",
				"header": [],
				"body": {
					"mode": "raw",
					"raw": "{\r\n    \"name\": \"morpheus\",\r\n    \"job\": \"zion resident\"\r\n}",
					"options": {
						"raw": {
							"language": "json"
						}
					}
				},
				"url": {
					"raw": "{{baseurl}}/api/users/2",
					"host": [
						"{{baseurl}}"
					],
					"path": [
						"api",
						"users",
						"2"
					]
				}
			},
			"response": []
		},
		{
			"name": "New Request",
			"request": {
				"method": "DELETE",
				"header": [],
				"url": {
					"raw": "{{baseurl}}/api/users/2",
					"host": [
						"{{baseurl}}"
					],
					"path": [
						"api",
						"users",
						"2"
					]
				}
			},
			"response": []
		}
	]
}